pyfastpaper/__init__.py
pyfastpaper/pyfastpaper.py
pyfastpaper-2.1.7.dist-info/LICENSE
pyfastpaper-2.1.7.dist-info/METADATA
pyfastpaper-2.1.7.dist-info/WHEEL
pyfastpaper-2.1.7.dist-info/top_level.txt
pyfastpaper-2.1.7.dist-info/RECORD
