Metadata-Version: 2.1
Name: pyfastpaper
Version: 2.1.7
Summary: 适合科研人员的Python快速绘图工具2.0版本！A Python tool for researchers to create figures for academic papers! V2.0.
Author-email: Yu-Xin Tian <neu.tianyuxin.2013@gmail.com>
Project-URL: Homepage, https://github.com/Jesse-tien/pyfastpaper
Project-URL: Bug Tracker, https://github.com/Jesse-tien/pyfastpaper/issues
Classifier: Programming Language :: Python :: 3
Classifier: License :: OSI Approved :: MIT License
Classifier: Operating System :: OS Independent
Requires-Python: >=3.8
License-File: LICENSE
Requires-Dist: numpy
Requires-Dist: sympy
Requires-Dist: matplotlib
Requires-Dist: ipython
Requires-Dist: notebook
